{
  "fetchedAt": "2026-04-30T20:38:45.882Z",
  "pageCount": 60,
  "successfulPages": 60,
  "failedPages": 0,
  "byCategory": {
    "tickets": [
      "https://www.texassandfest.org/",
      "https://www.eventeny.com/events/texas-sandfest-2026-21603/",
      "https://www.eventeny.com/events/ticket/?id=21603",
      "https://www.texassandfest.org/golf-cart-raffle",
      "https://www.texassandfest.org/generaladmissionticket",
      "https://www.texassandfest.org/bollard-buddies",
      "https://www.texassandfest.org/vipwristbands",
      "https://www.texassandfest.org"
    ],
    "visitor": [
      "https://www.texassandfest.org/maps",
      "https://www.texassandfest.org/accessibility",
      "https://www.texassandfest.org/faq",
      "https://www.texassandfest.org/getting-to-sandfest",
      "https://www.texassandfest.org/parking-shuttles",
      "https://www.texassandfest.org/ferry",
      "https://www.texassandfest.org/petpolicy"
    ],
    "program": [
      "https://www.texassandfest.org/daily-schedule",
      "https://www.texassandfest.org/copy-of-at-sandfest",
      "https://www.texassandfest.org/at-sandfest",
      "https://www.texassandfest.org/kidscorner",
      "https://www.texassandfest.org/livemusic",
      "https://www.texassandfest.org/copy-of-live-music",
      "https://www.texassandfest.org/live-music",
      "https://www.texassandfest.org/things-to-do"
    ],
    "competition": [
      "https://www.texassandfest.org/advancedamateurs",
      "https://www.texassandfest.org/winners",
      "https://www.texassandfest.org/amateur-competition",
      "https://www.texassandfest.org/master-duo-sculptors",
      "https://www.texassandfest.org/sculptors/master-solo-sculptors",
      "https://www.texassandfest.org/master-solo-sculptors2024",
      "https://www.texassandfest.org/sculptors",
      "https://www.texassandfest.org/non-competing-sculptors",
      "https://www.texassandfest.org/semi-pro-sculptors",
      "https://www.texassandfest.org/master-duo-sculptors2024"
    ],
    "partner": [
      "https://www.texassandfest.org/get-involved",
      "https://www.texassandfest.org/volunteer",
      "https://www.texassandfest.org/sponsorship",
      "https://www.texassandfest.org/vendors"
    ],
    "organization": [
      "https://www.texassandfest.org/sustainablity",
      "https://www.texassandfest.org/copy-of-press-release",
      "https://www.texassandfest.org/magazine",
      "https://www.texassandfest.org/history",
      "https://www.texassandfest.org/board",
      "https://www.texassandfest.org/mission",
      "https://www.texassandfest.org/contact-us",
      "https://www.texassandfest.org/about",
      "https://www.texassandfest.org/pressrelease",
      "https://www.texassandfest.org/guestsurvey"
    ],
    "commerce": [
      "https://www.texassandfest.org/product-page/i-m-a-product-9",
      "https://www.texassandfest.org/product-page/i-m-a-product-10",
      "https://www.texassandfest.org/product-page/i-m-a-product-1",
      "https://www.texassandfest.org/product-page/i-m-a-product-5",
      "https://www.texassandfest.org/product-page/i-m-a-product-11",
      "https://www.texassandfest.org/product-page/i-m-a-product-3",
      "https://www.texassandfest.org/product-page/i-m-a-product-8",
      "https://www.texassandfest.org/product-page/i-m-a-product-7",
      "https://www.texassandfest.org/product-page/i-m-a-product",
      "https://www.texassandfest.org/product-page/i-m-a-product-2",
      "https://www.texassandfest.org/product-page/i-m-a-product-6",
      "https://www.texassandfest.org/product-page/i-m-a-product-4",
      "https://www.texassandfest.org/category/all-products"
    ]
  },
  "eventenyLinks": [
    "https://www.eventeny.com/",
    "https://www.eventeny.com/pride/",
    "https://www.eventeny.com/mapping/",
    "https://www.eventeny.com/ticketing/",
    "https://www.eventeny.com/vendor-management/",
    "https://www.eventeny.com/volunteer-management-tools/",
    "https://www.eventeny.com/sponsors/",
    "https://www.eventeny.com/program-management/",
    "https://www.eventeny.com/schedule/",
    "https://www.eventeny.com/hardware-rentals/",
    "https://www.eventeny.com/organizer-app/",
    "https://www.eventeny.com/event-management-software/",
    "https://www.eventeny.com/why-eventeny/",
    "https://www.eventeny.com/about/about-us/",
    "https://www.eventeny.com/product/pricing/",
    "https://help.eventeny.com/",
    "https://www.eventeny.com/community/",
    "https://www.eventeny.com/compare/",
    "https://resources.eventeny.com/",
    "https://www.eventeny.com/contact-sales/",
    "https://www.eventeny.com/whats-new-in-eventeny/",
    "https://www.eventeny.com/case-studies/",
    "https://www.eventeny.com/users/?ref=/dashboard/events/",
    "https://www.eventeny.com/users/?ref=/dashboard/events/?create",
    "https://www.eventeny.com/users/?ref=/users/application/",
    "https://www.eventeny.com/users/account-settings/product-setup/",
    "https://www.eventeny.com/users/?ref=/users/account-settings/orders/sales/",
    "https://www.eventeny.com/users/?ref=/users/show/",
    "https://www.eventeny.com/users/?ref=/users/account-settings/orders/purchases/",
    "https://www.eventeny.com/events/applications/",
    "https://www.eventeny.com/product/mobile-app/",
    "https://www.eventeny.com/events/",
    "https://www.eventeny.com/users/?ref=/events/texas-sandfest-2026-21603/",
    "https://www.eventeny.com/users/signup/?ref=/events/texas-sandfest-2026-21603/",
    "https://www.eventeny.com/dashboard/events/?create",
    "https://www.eventeny.com/users/",
    "https://www.eventeny.com/users/signup",
    "https://www.eventeny.com/company/?c=65806",
    "https://www.eventeny.com/company/?c=440449",
    "https://www.eventeny.com/company/?c=189974",
    "https://www.eventeny.com/company/?c=483246",
    "https://www.eventeny.com/company/?c=90822",
    "https://www.eventeny.com/company/?c=313231",
    "https://www.eventeny.com/company/?c=78644",
    "https://www.eventeny.com/company/?c=467418",
    "https://www.eventeny.com/company/?c=87521",
    "https://www.eventeny.com/company/?c=331353",
    "https://www.eventeny.com/company/?c=459064",
    "https://www.eventeny.com/company/?c=324515",
    "https://www.eventeny.com/inbox/conversation/?in&to=1599110",
    "https://www.eventeny.com/events/ticket/?id=21603",
    "https://www.eventeny.com/users/?ref=https://www.eventeny.com/events/texas-sandfest-2026-21603/",
    "https://www.eventeny.com/legal/privacy/",
    "https://www.eventeny.com/legal/cookie-policy/",
    "https://www.eventeny.com/company/product/",
    "https://www.eventeny.com/reviews/",
    "https://www.eventeny.com/food-drink-event-management-software/",
    "https://www.eventeny.com/art-festival-management-software/",
    "https://www.eventeny.com/community-event-management-software/",
    "https://www.eventeny.com/fair-management-software/",
    "https://www.eventeny.com/fandom-event-management-software/",
    "https://www.eventeny.com/pride-event-management-software/",
    "https://www.eventeny.com/music-festival-management-software/",
    "https://www.eventeny.com/markets-management-software/",
    "https://www.eventeny.com/heritage-festival-management-software/",
    "https://www.eventeny.com/refer/",
    "https://www.eventeny.com/partnerships/",
    "https://www.eventeny.com/plantastic-events-podcast/",
    "https://www.eventeny.com/eventeny-media-kit/",
    "https://www.eventeny.com/event-management-resources/",
    "https://www.eventeny.com/welcome-artists-vendors/",
    "https://www.eventeny.com/giving-back/",
    "https://www.eventeny.com/about/careers/",
    "https://www.eventeny.com/accessibility/",
    "https://www.eventeny.com/legal/terms-of-service/",
    "https://www.eventeny.com/security/",
    "https://help.eventeny.com/hc/en-us",
    "https://www.eventeny.com/events/?q=&l=&m=",
    "https://www.eventeny.com/legal/acceptable-use-policy/",
    "https://www.eventeny.com/users/?ref=/events/ticket/?id=21603",
    "https://www.eventeny.com/users/signup/?ref=/events/ticket/?id=21603",
    "https://www.eventeny.com/events/texas-sandfest-2026-21603/",
    "https://www.eventeny.com/inbox/?to=280170&event=21603&type=1",
    "https://www.eventeny.com/about/contact-us/",
    "https://www.eventeny.com/events/ticket/?id=21603&amp;type=tickets&amp;show=custom&amp;custom=47451",
    "https://www.eventeny.com/events/ticket/?id=21603&amp;type=tickets&amp;show=custom&amp;custom=39512",
    "https://www.eventeny.com/events/texas-sandfest-2025-7959/?action=vendor",
    "https://www.eventeny.com/events/texas-sandfest-2026-21603/?action=sponsor"
  ],
  "sandfestEventenyLinks": [
    "https://www.eventeny.com/users/?ref=/events/texas-sandfest-2026-21603/",
    "https://www.eventeny.com/users/signup/?ref=/events/texas-sandfest-2026-21603/",
    "https://www.eventeny.com/inbox/conversation/?in&to=1599110",
    "https://www.eventeny.com/events/ticket/?id=21603",
    "https://www.eventeny.com/users/?ref=https://www.eventeny.com/events/texas-sandfest-2026-21603/",
    "https://www.eventeny.com/users/?ref=/events/ticket/?id=21603",
    "https://www.eventeny.com/users/signup/?ref=/events/ticket/?id=21603",
    "https://www.eventeny.com/events/texas-sandfest-2026-21603/",
    "https://www.eventeny.com/inbox/?to=280170&event=21603&type=1",
    "https://www.eventeny.com/events/ticket/?id=21603&amp;type=tickets&amp;show=custom&amp;custom=47451",
    "https://www.eventeny.com/events/ticket/?id=21603&amp;type=tickets&amp;show=custom&amp;custom=39512",
    "https://www.eventeny.com/events/texas-sandfest-2025-7959/?action=vendor",
    "https://www.eventeny.com/events/texas-sandfest-2026-21603/?action=sponsor"
  ],
  "socialLinks": [
    "https://www.instagram.com/texas_sandfest/",
    "https://www.facebook.com/TexasSandFest/",
    "https://www.facebook.com/eventeny/",
    "https://twitter.com/eventenyteam/",
    "https://www.linkedin.com/company/eventeny/",
    "https://www.instagram.com/eventenyteam/",
    "https://www.tiktok.com/@eventeny/",
    "https://www.facebook.com/blacksheepsoulatx",
    "https://www.facebook.com/yarnbombinginporta/",
    "https://www.facebook.com/PortAransasVFW",
    "https://www.facebook.com/PortAransasPoliceFoundation",
    "https://x.com/PortA_Ferry",
    "http://www.facebook.com/sharer.php?u=https%3A%2F%2Fwww.texassandfest.org%2Fproduct-page%2Fi-m-a-product-9&amp;title=I&#x27;m+a+product",
    "https://twitter.com/intent/tweet?url=https%3A%2F%2Fwww.texassandfest.org%2Fproduct-page%2Fi-m-a-product-9&amp;text=I&#x27;m+a+product%0A",
    "http://www.facebook.com/sharer.php?u=https%3A%2F%2Fwww.texassandfest.org%2Fproduct-page%2Fi-m-a-product-10&amp;title=I&#x27;m+a+product",
    "https://twitter.com/intent/tweet?url=https%3A%2F%2Fwww.texassandfest.org%2Fproduct-page%2Fi-m-a-product-10&amp;text=I&#x27;m+a+product%0A",
    "http://www.facebook.com/sharer.php?u=https%3A%2F%2Fwww.texassandfest.org%2Fproduct-page%2Fi-m-a-product-1&amp;title=I&#x27;m+a+product",
    "https://twitter.com/intent/tweet?url=https%3A%2F%2Fwww.texassandfest.org%2Fproduct-page%2Fi-m-a-product-1&amp;text=I&#x27;m+a+product%0A",
    "http://www.facebook.com/sharer.php?u=https%3A%2F%2Fwww.texassandfest.org%2Fproduct-page%2Fi-m-a-product-11&amp;title=I&#x27;m+a+product",
    "https://twitter.com/intent/tweet?url=https%3A%2F%2Fwww.texassandfest.org%2Fproduct-page%2Fi-m-a-product-11&amp;text=I&#x27;m+a+product%0A",
    "http://www.facebook.com/sharer.php?u=https%3A%2F%2Fwww.texassandfest.org%2Fproduct-page%2Fi-m-a-product-3&amp;title=I&#x27;m+a+product",
    "https://twitter.com/intent/tweet?url=https%3A%2F%2Fwww.texassandfest.org%2Fproduct-page%2Fi-m-a-product-3&amp;text=I&#x27;m+a+product%0A",
    "http://www.facebook.com/sharer.php?u=https%3A%2F%2Fwww.texassandfest.org%2Fproduct-page%2Fi-m-a-product-8&amp;title=I&#x27;m+a+product",
    "https://twitter.com/intent/tweet?url=https%3A%2F%2Fwww.texassandfest.org%2Fproduct-page%2Fi-m-a-product-8&amp;text=I&#x27;m+a+product%0A",
    "http://www.facebook.com/sharer.php?u=https%3A%2F%2Fwww.texassandfest.org%2Fproduct-page%2Fi-m-a-product-7&amp;title=I&#x27;m+a+product",
    "https://twitter.com/intent/tweet?url=https%3A%2F%2Fwww.texassandfest.org%2Fproduct-page%2Fi-m-a-product-7&amp;text=I&#x27;m+a+product%0A",
    "http://www.facebook.com/sharer.php?u=https%3A%2F%2Fwww.texassandfest.org%2Fproduct-page%2Fi-m-a-product&amp;title=I&#x27;m+a+product",
    "https://twitter.com/intent/tweet?url=https%3A%2F%2Fwww.texassandfest.org%2Fproduct-page%2Fi-m-a-product&amp;text=I&#x27;m+a+product%0A",
    "http://www.facebook.com/sharer.php?u=https%3A%2F%2Fwww.texassandfest.org%2Fproduct-page%2Fi-m-a-product-2&amp;title=I&#x27;m+a+product",
    "https://twitter.com/intent/tweet?url=https%3A%2F%2Fwww.texassandfest.org%2Fproduct-page%2Fi-m-a-product-2&amp;text=I&#x27;m+a+product%0A",
    "http://www.facebook.com/sharer.php?u=https%3A%2F%2Fwww.texassandfest.org%2Fproduct-page%2Fi-m-a-product-4&amp;title=I&#x27;m+a+product",
    "https://twitter.com/intent/tweet?url=https%3A%2F%2Fwww.texassandfest.org%2Fproduct-page%2Fi-m-a-product-4&amp;text=I&#x27;m+a+product%0A"
  ],
  "documents": [
    "https://assets.simpleviewinc.com/simpleview/image/upload/v1/clients/portaransastx/2023_Detailed_Street_Map_Back_98fa7b66-86ba-44c9-9d4f-99aab1c94cb8.pdf",
    "https://www.texassandfest.org/_files/ugd/f800df_e5cf5ff6492f4698904263d7fe3fd1ac.pdf"
  ],
  "sourceSitemaps": [
    "https://www.texassandfest.org/sitemap.xml",
    "https://www.texassandfest.org/pages-sitemap.xml",
    "https://www.texassandfest.org/store-products-sitemap.xml",
    "https://www.texassandfest.org/store-categories-sitemap.xml"
  ]
}
